inkex_bh/__init__.py
inkex_bh/_compat.py
inkex_bh/constants.py
inkex_bh/count_symbols.py
inkex_bh/create_inset.py
inkex_bh/debug.py
inkex_bh/hide_rats.py
inkex_bh/random_seed.py
inkex_bh/typing.py
inkex_bh/update_symbols.py
inkex_bh/workarounds.py
inkex_bh/extensions/count-symbols.inx
inkex_bh/extensions/create-inset.inx
inkex_bh/extensions/hide-rats.inx
inkex_bh/extensions/random-seed.inx
inkex_bh/extensions/run-module.py
inkex_bh/extensions/update-symbols.inx
inkex_bh-1.0.1.dist-info/METADATA
inkex_bh-1.0.1.dist-info/WHEEL
inkex_bh-1.0.1.dist-info/licenses/COPYING
inkex_bh-1.0.1.dist-info/RECORD
