Metadata-Version: 2.3
Name: inkex-bh
Version: 1.0.1
Summary: Inkscape extensions for Barn Hunt
Project-URL: Homepage, https://github.com/barnhunt/inkex-bh
Author-email: Jeff Dairiki <dairiki@dairiki.org>
License: GNU GPLv3
Keywords: barn hunt,barnhunt,inkscape
Classifier: Development Status :: 4 - Beta
Classifier: Environment :: Plugins
Classifier: Intended Audience :: End Users/Desktop
Classifier: Intended Audience :: Other Audience
Classifier: License :: OSI Approved :: GNU General Public License v3 (GPLv3)
Classifier: Programming Language :: Python :: 3
Classifier: Topic :: Artistic Software
Classifier: Topic :: Multimedia :: Graphics
Classifier: Topic :: Multimedia :: Graphics :: Editors
Classifier: Topic :: Multimedia :: Graphics :: Editors :: Vector-Based
Classifier: Typing :: Typed
Requires-Python: >=3.8
Requires-Dist: lxml
